lattice_llm/__init__.py
lattice_llm/bedrock/__init__.py
lattice_llm/bedrock/client.py
lattice_llm/bedrock/converse.py
lattice_llm/bedrock/messages.py
lattice_llm/bedrock/models.py
lattice_llm/bedrock/tools.py
lattice_llm/graph/__init__.py
lattice_llm/graph/execution.py
lattice_llm/graph/graph.py
lattice_llm/py.typed
lattice_llm/state/__init__.py
lattice_llm/state/local_state_store.py
lattice_llm/state/state_store.py
lattice_llm/util.py
lattice_llm-0.1.2.dist-info/LICENSE
lattice_llm-0.1.2.dist-info/METADATA
lattice_llm-0.1.2.dist-info/WHEEL
lattice_llm-0.1.2.dist-info/RECORD
